vfs_merge/__init__.py
vfs_merge/__main__.py
vfs_merge/create_littlefs.py
vfs_merge/picotool.exe
vfs_merge/portboard_disk.md
vfs_merge/portboard_disk.py
vfs_merge/sources.md
vfs_merge/uf2_tool.py
vfs_merge/uf2conv.py
vfs_merge/uf2families.json
vfs_merge/walk.py
vfs_merge-0.1.2.dist-info/entry_points.txt
vfs_merge-0.1.2.dist-info/LICENSE
vfs_merge-0.1.2.dist-info/METADATA
vfs_merge-0.1.2.dist-info/WHEEL
vfs_merge-0.1.2.dist-info/RECORD
