Metadata-Version: 2.1
Name: vfs-merge
Version: 0.1.2
Summary: Merge a MicroPython firmware and with source files into a single binary that can be flashed to a device.
License: MIT
Author: Jos Verlinde
Author-email: jos_verlinde@hotmail.com
Requires-Python: >=3.8,<4.0
Classifier: License :: OSI Approved :: MIT License
Classifier: Programming Language :: Python :: 3
Classifier: Programming Language :: Python :: 3.8
Classifier: Programming Language :: Python :: 3.9
Classifier: Programming Language :: Python :: 3.10
Classifier: Programming Language :: Python :: 3.11
Requires-Dist: esptool (==4.5)
Requires-Dist: littlefs-python (>=0.8.0,<0.9.0)
Requires-Dist: loguru (>=0.7.2,<0.8.0)
Requires-Dist: python-dotenv (>=1.0.0,<2.0.0)
